metalayer/__init__.py
metalayer/cache.py
metalayer/consumer.py
metalayer/embeddings.py
metalayer/main.py
metalayer/obsidianize.py
metalayer/ocr.py
metalayer/ocr_heuristics.py
metalayer/producer.py
metalayer/reindex.py
metalayer/setup.py
metalayer/system.py
metalayer/utils.py
metalayer/auto_obsidian/__init__.py
metalayer/auto_obsidian/engine.py
metalayer/auto_obsidian/graph.py
metalayer/chatgpt/__init__.py
metalayer/chatgpt/activity_log.py
metalayer/chatgpt/chatgpt.py
metalayer/chatgpt/chatgpt_server.py
metalayer/chatgpt/info_extraction.py
metalayer/chatgpt/logger.py
metalayer/chatgpt/ocr_filtering.py
metalayer/chatgpt/utils.py
metalayer/chatgpt/prompts/activity_log/user.txt
metalayer/chatgpt/prompts/info_extraction/system.txt
metalayer/chatgpt/prompts/info_extraction/user.txt
metalayer/chatgpt/prompts/ocr_filtering/user.txt
metalayer/macos/__init__.py
metalayer/macos/applescript.py
metalayer/macos/battery.py
metalayer/macos/capture.py
metalayer/macos/ocr.py
metalayer/macos/utils.py
auto_obsidian-0.1.3.dist-info/METADATA
auto_obsidian-0.1.3.dist-info/WHEEL
auto_obsidian-0.1.3.dist-info/entry_points.txt
auto_obsidian-0.1.3.dist-info/top_level.txt
auto_obsidian-0.1.3.dist-info/RECORD
