Metadata-Version: 2.1
Name: auto-obsidian
Version: 0.1.3
Summary: A layer on top of your OS that understands what you're doing
Author: Ivan Yevenko
Author-email: iyevenko@gmail.com
License: MIT
Requires-Python: >=3.8
Requires-Dist: easyocr (==1.7.0)
Requires-Dist: Levenshtein (==0.21.0)
Requires-Dist: matplotlib (==3.6.1)
Requires-Dist: nltk (==3.7)
Requires-Dist: numpy (==1.24.3)
Requires-Dist: openai (==0.27.6)
Requires-Dist: opencv-python (==4.6.0.66)
Requires-Dist: parse (==1.19.0)
Requires-Dist: Pillow (==9.5.0)
Requires-Dist: pynput (==1.7.6)
Requires-Dist: pyobjc (==9.0.1)
Requires-Dist: requests (==2.31.0)
Requires-Dist: tqdm (==4.64.1)
Requires-Dist: transformers (==4.23.1)
Requires-Dist: watchdog (==3.0.0)
